fed_requests/__init__.py
fed_requests/fedbionet_api.py
fed_requests/loggers.py
fed_requests/model_zoo.py
fed_requests/settings.py
fed_requests-0.0.34.dist-info/LICENSE
fed_requests-0.0.34.dist-info/METADATA
fed_requests-0.0.34.dist-info/WHEEL
fed_requests-0.0.34.dist-info/top_level.txt
fed_requests-0.0.34.dist-info/RECORD
